endless_sdk/__init__.py
endless_sdk/account.py
endless_sdk/account_address.py
endless_sdk/account_sequence_number.py
endless_sdk/api_config.py
endless_sdk/asymmetric_crypto.py
endless_sdk/asymmetric_crypto_wrapper.py
endless_sdk/async_client.py
endless_sdk/authenticator.py
endless_sdk/bcs.py
endless_sdk/cli.py
endless_sdk/ed25519.py
endless_sdk/endless_cli_wrapper.py
endless_sdk/endless_token_client.py
endless_sdk/endless_tokenv1_client.py
endless_sdk/metadata.py
endless_sdk/package_publisher.py
endless_sdk/secp256k1_ecdsa.py
endless_sdk/transaction_worker.py
endless_sdk/transactions.py
endless_sdk/type_tag.py
endless_sdk-1.0.0.dist-info/LICENSE
endless_sdk-1.0.0.dist-info/METADATA
endless_sdk-1.0.0.dist-info/WHEEL
endless_sdk-1.0.0.dist-info/RECORD
