Metadata-Version: 2.3
Name: endless-sdk
Version: 1.0.0
Summary: Endless SDK
License: Apache-2.0
Keywords: web3,sdk,endless,blockchain,python
Author: Niraj Kulkarni
Author-email: niraj.kulkarni@surrey.ac.uk
Requires-Python: >=3.8.1
Classifier: License :: OSI Approved :: Apache Software License
Classifier: Programming Language :: Python :: 3
Classifier: Programming Language :: Python :: 3.9
Classifier: Programming Language :: Python :: 3.10
Classifier: Programming Language :: Python :: 3.11
Classifier: Programming Language :: Python :: 3.12
Classifier: Programming Language :: Python :: 3.13
Requires-Dist: PyNaCl (>=1.5.0,<2.0.0)
Requires-Dist: aiohttp (>=3.0.0,<4.0.0)
Requires-Dist: base58 (>=2.1.1,<3.0.0)
Requires-Dist: behave (>=1.2.6,<2.0.0)
Requires-Dist: ecdsa (==0.18.0)
Requires-Dist: httpx (>=0.27.0,<0.28.0)
Requires-Dist: python-graphql-client (>=0.4.3,<0.5.0)
Requires-Dist: tomli (>=2.0.1,<3.0.0)
Requires-Dist: types-six (>=1.16.21.20240513,<2.0.0.0)
Requires-Dist: typing-extensions (>=4.4.0,<5.0.0)
